pygrambot/__init__.py
pygrambot/bot/__init__.py
pygrambot/bot/config.py
pygrambot/bot/middlewares.py
pygrambot/bot/botcommands/__init__.py
pygrambot/bot/botcommands/api_commands.py
pygrambot/bot/botcommands/commands.py
pygrambot/bot/bothandlers/__init__.py
pygrambot/bot/bothandlers/bot.py
pygrambot/bot/bothandlers/handlers.py
pygrambot/cli/__init__.py
pygrambot/cli/bot_cli.py
pygrambot/cli/templates/__init__.py
pygrambot/cli/templates/bot_settings.py
pygrambot/data_objects/__init__.py
pygrambot/data_objects/objects.py
pygrambot/exceptions/__init__.py
pygrambot/exceptions/base.py
pygrambot/exceptions/main_exc.py
pygrambot/telegram/__init__.py
pygrambot/telegram/keyboards.py
pygrambot-1.2.0.dist-info/METADATA
pygrambot-1.2.0.dist-info/WHEEL
pygrambot-1.2.0.dist-info/top_level.txt
pygrambot-1.2.0.dist-info/RECORD
