Metadata-Version: 2.1
Name: pygrambot
Version: 1.2.0
Summary: Framework for creating telegram bots.
Classifier: Programming Language :: Python :: 3
Requires-Python: >=3.7
